{
	"class" : {
		 },
	"instance" : {
		"blockingExecute" : "HolgerHansPeterFreyther 5/28/2016 23:18:55",
		"connectionName:" : "HolgerHansPeterFreyther 5/28/2016 23:18:55",
		"createCommandForMessage:" : "HolgerHansPeterFreyther 5/28/2016 23:18:55",
		"deliveredMessage:" : "HolgerHansPeterFreyther 5/28/2016 23:18:55",
		"failMessage:" : "HolgerHansPeterFreyther 5/28/2016 23:18:55",
		"pendingMessages" : "HolgerHansPeterFreyther 5/28/2016 23:18:55",
		"sendMessage:on:" : "HolgerHansPeterFreyther 5/28/2016 23:18:55",
		"sendMessagesOn:" : "HolgerHansPeterFreyther 5/28/2016 23:18:55" } }
